Metadata-Version: 2.1
Name: my-typing-game1
Version: 1.0.0
Summary: Testing package - game
Author: my
Author-email: john.doe@gmail.com
